{
    "/js/app.js": "/js/app.js?id=639741e4016361c50e3d",
    "/css/app-ltr.css": "/css/app-ltr.css?id=abd679421f2401ea4f13",
    "/css/app-rtl.css": "/css/app-rtl.css?id=6a510697c0dfc75a6b63",
    "/css/stripe.css": "/css/stripe.css?id=75b003369e14951730ae",
    "/js/manifest.js": "/js/manifest.js?id=844cdbfe9e6b6b56ae8f",
    "/js/stripe.js": "/js/stripe.js?id=5422c45d41fa631d5229",
    "/js/vendor.js": "/js/vendor.js?id=29eade29098eb7d95016",
    "/js/u2f-api.js": "/js/u2f-api.js?id=2cb142068f47a614b35d"
}
